cleantam/__init__.py
cleantam/core.py
cleantam-0.1.1.dist-info/LICENSE
cleantam-0.1.1.dist-info/METADATA
cleantam-0.1.1.dist-info/WHEEL
cleantam-0.1.1.dist-info/top_level.txt
cleantam-0.1.1.dist-info/RECORD
