Metadata-Version: 2.1
Name: cleantam
Version: 0.1.1
Summary: Una extensión de Pandas para limpiar datos con formato latinoamericano
Home-page: https://github.com/fedco-gtz/cleantam
Author: Federico Gabriel Gutierrez
Author-email: gutierrezfedericog@gmail.com
Classifier: Programming Language :: Python :: 3
Classifier: License :: OSI Approved :: MIT License
Classifier: Operating System :: OS Independent
Requires-Python: >=3.6
License-File: LICENSE
Requires-Dist: pandas
